minislite/__init__.py
minislite/exceptions.py
minislite/fields.py
minislite/minislite.py
minislite/models.py
minislite/objects.py
minislite/sql.py
minislite/tables.py
minislite-0.99.dist-info/METADATA
minislite-0.99.dist-info/WHEEL
minislite-0.99.dist-info/top_level.txt
minislite-0.99.dist-info/RECORD
