Metadata-Version: 2.1
Name: minislite
Version: 0.99
Summary: Mini and Secure SQLite ORM
Home-page: https://github.com/ahmetkotan/minislite
Author: ahmetkotan
Author-email: ahmtkotan@gmail.com
License: UNKNOWN
Platform: UNKNOWN
Classifier: Programming Language :: Python :: 3
Classifier: Programming Language :: SQL
Classifier: License :: OSI Approved :: MIT License
Classifier: Operating System :: OS Independent
Classifier: Topic :: Database
Classifier: Topic :: Database :: Database Engines/Servers
